paho-stubs/METADATA.toml
paho-stubs/__init__.pyi
paho-stubs/mqtt/__init__.pyi
paho-stubs/mqtt/client.pyi
paho-stubs/mqtt/matcher.pyi
paho-stubs/mqtt/packettypes.pyi
paho-stubs/mqtt/properties.pyi
paho-stubs/mqtt/publish.pyi
paho-stubs/mqtt/reasoncodes.pyi
paho-stubs/mqtt/subscribe.pyi
paho-stubs/mqtt/subscribeoptions.pyi
types_paho_mqtt-1.6.0.20240106.dist-info/METADATA
types_paho_mqtt-1.6.0.20240106.dist-info/WHEEL
types_paho_mqtt-1.6.0.20240106.dist-info/top_level.txt
types_paho_mqtt-1.6.0.20240106.dist-info/RECORD
